majormode/__init__.py
majormode/xebus/__init__.py
majormode/xebus/client/__init__.py
majormode/xebus/client/service/__init__.py
majormode/xebus/client/service/admin_service.py
majormode/xebus/client/service/attendant_service.py
majormode/xebus/client/service/bus_route_service.py
majormode/xebus/client/service/child_service.py
majormode/xebus/client/service/education_service.py
majormode/xebus/client/service/guardian_service.py
majormode/xebus/client/service/messaging_service.py
majormode/xebus/client/service/school_service.py
majormode/xebus/client/service/upmd_service.py
majormode/xebus/client/service/xebus_service.py
xebus_restful_api_client_library-1.9.2.dist-info/METADATA
xebus_restful_api_client_library-1.9.2.dist-info/WHEEL
xebus_restful_api_client_library-1.9.2.dist-info/top_level.txt
xebus_restful_api_client_library-1.9.2.dist-info/RECORD
