Metadata-Version: 2.1
Name: xebus-restful-api-client-library
Version: 1.9.2
Summary: Xebus RESTful API Client Python Library
Home-page: UNKNOWN
Author: Daniel CAUNE
Author-email: daniel.caune@majormode.com
License: Copyright (C) 2019, Majormode
Platform: any
Classifier: License :: OSI Approved :: GNU General Public License (GPL)
Classifier: Development Status :: 5 - Production/Stable
Classifier: Topic :: Software Development :: Libraries :: Python Modules
Classifier: Programming Language :: Python
Requires-Python: >=3
Requires-Dist: perseus-restful-api-client-library
Requires-Dist: xebus-core-library
